{
  "version": "1.0",
  "codes": {
    "EMO": {
      "label": "Emotional / loaded language",
      "depict": "Emotion"
    },
    "URG": {
      "label": "Urgency / pressure cues",
      "depict": "Emotion+Trolling"
    },
    "ANON": {
      "label": "Anonymous or vague attribution",
      "depict": "Impersonation"
    },
    "MISS": {
      "label": "Missing evidence (no link, no named source)",
      "depict": "Composite (no source / no link)"
    },
    "FAB": {
      "label": "Fabricated-quote risk",
      "depict": "Impersonation"
    },
    "POL": {
      "label": "Polarising in-group / out-group framing",
      "depict": "Polarization"
    },
    "CONS": {
      "label": "Conspiratorial reasoning",
      "depict": "Conspiracy"
    },
    "DISC": {
      "label": "Discrediting / personal attack",
      "depict": "Discrediting"
    },
    "IMP": {
      "label": "Impersonation / fake authority",
      "depict": "Impersonation"
    },
    "REV": {
      "label": "Historical revisionism",
      "depict": "Filipino-specific (Arugay & Baquisal 2022)"
    },
    "ENDO": {
      "label": "Manufactured survey or fake endorsement",
      "depict": "Filipino-specific (manufactured surveys/endorsements)"
    },
    "RECF": {
      "label": "Candidate-record fabrication",
      "depict": "Filipino-specific (candidate-record fabrication)"
    }
  },
  "depict_taxonomy": "Roozenbeek & van der Linden (2019); Basol, Roozenbeek & van der Linden (2020); extended for Filipino electoral context per Arugay & Baquisal (2022) and Schipper (2025)."
}